fragua/__init__.py
fragua/py.typed
fragua/core/__init__.py
fragua/core/agent.py
fragua/core/component.py
fragua/core/environment.py
fragua/core/registry.py
fragua/core/set.py
fragua/core/storage.py
fragua/core/warehouse.py
fragua/registry/__init__.py
fragua/registry/registry.py
fragua/sets/__init__.py
fragua/sets/extract/__init__.py
fragua/sets/extract/functions.py
fragua/sets/load/__init__.py
fragua/sets/load/functions.py
fragua/sets/load/internal_functions.py
fragua/sets/transform/__init__.py
fragua/sets/transform/functions.py
fragua/sets/transform/internal_functions.py
fragua/utils/__init__.py
fragua/utils/logger/__init__.py
fragua/utils/logger/logger.py
fragua/utils/metrics/__init__.py
fragua/utils/metrics/metadata.py
fragua/utils/metrics/metrics.py
fragua/utils/metrics/serializers.py
fragua/utils/security/__init__.py
fragua/utils/security/security_context.py
fragua/utils/types/__init__.py
fragua/utils/types/enums.py
fragua-0.9.0.dist-info/licenses/LICENSE
fragua-0.9.0.dist-info/METADATA
fragua-0.9.0.dist-info/WHEEL
fragua-0.9.0.dist-info/top_level.txt
fragua-0.9.0.dist-info/RECORD
