Metadata-Version: 2.4
Name: fragua
Version: 0.9.0
Summary: Package for creating ETL environments for data analysis
Home-page: https://github.com/SagoDev/Fragua
Author: SagoDev
Requires-Python: >=3.10
License-File: LICENSE
Requires-Dist: numpy
Requires-Dist: pandas
Requires-Dist: sqlalchemy
Requires-Dist: requests
Requires-Dist: scikit-learn
Dynamic: author
Dynamic: description
Dynamic: description-content-type
Dynamic: home-page
Dynamic: license-file
Dynamic: requires-dist
Dynamic: requires-python
Dynamic: summary
